MANIFEST.in
README.md
setup.py
appmedia/BeautifulSoup.py
appmedia/__init__.py
appmedia/api.py
appmedia/middleware.py
appmedia/models.py
appmedia/urls.py
appmedia/views.py
appmedia/management/__init__.py
appmedia/management/commands/__init__.py
appmedia/management/commands/buildmedia.py
appmedia/management/commands/symlinkmedia.py
django_appmedia.egg-info/PKG-INFO
django_appmedia.egg-info/SOURCES.txt
django_appmedia.egg-info/dependency_links.txt
django_appmedia.egg-info/not-zip-safe
django_appmedia.egg-info/top_level.txt