Metadata-Version: 1.1
Name: django-appmedia
Version: 1.0.1
Summary: Handling django app media
Home-page: http://github.com/divio/django-appmedia
Author: Patrick Lauber
Author-email: digi@treepy.com
License: UNKNOWN
Platform: OS Independent
Classifier: Development Status :: 5 - Production/Stable
Classifier: Environment :: Web Environment
Classifier: Framework :: Django
Classifier: Intended Audience :: Developers
Classifier: License :: OSI Approved :: BSD License
Classifier: Operating System :: OS Independent
Classifier: Programming Language :: Python
Classifier: Topic :: Internet :: WWW/HTTP :: Dynamic Content
Classifier: Topic :: Software Development
Classifier: Topic :: Software Development :: Libraries :: Application Frameworks
Requires: django (>1.1.0)
